[
  {
    "text": "MARTIN BARROSO JAVIER",
    "label": "Transporte",
    "confidence": 0.6707,
    "original": "TRANSFERENCIA A FAVOR DE MARTIN BARROSO JAVIER"
  },
  {
    "text": "MARTIN BARROSO JAVIER",
    "label": "Transporte",
    "confidence": 0.6707,
    "original": "TRANSFERENCIA A FAVOR DE MARTIN BARROSO JAVIER"
  },
  {
    "text": "aliexpress",
    "label": "Otros",
    "confidence": 0.6757,
    "original": "COMPRA EN aliexpress, CON LA TARJETA : 5489133182050904 EL 2026-01-20"
  },
  {
    "text": "MARTIN BARROSO JAVIER",
    "label": "Transporte",
    "confidence": 0.6707,
    "original": "TRANSFERENCIA A FAVOR DE MARTIN BARROSO JAVIER"
  },
  {
    "text": "MARTIN BARROSO JAVIER",
    "label": "Transporte",
    "confidence": 0.6707,
    "original": "TRANSFERENCIA A FAVOR DE MARTIN BARROSO JAVIER"
  },
  {
    "text": "MARTIN BARROSO JAVIER",
    "label": "Transporte",
    "confidence": 0.6707,
    "original": "TRANSFERENCIA A FAVOR DE MARTIN BARROSO JAVIER"
  },
  {
    "text": "aliexpress",
    "label": "Otros",
    "confidence": 0.6757,
    "original": "COMPRA EN aliexpress, CON LA TARJETA : 5489133182050904 EL 2025-11-12"
  },
  {
    "text": "Santa Julia",
    "label": "Ocio",
    "confidence": 0.2801,
    "original": "COMPRA EN Santa Julia, CON LA TARJETA : 5489133182050904 EL 2025-11-04"
  },
  {
    "text": "Santa Julia",
    "label": "Ocio",
    "confidence": 0.2801,
    "original": "COMPRA EN Santa Julia, CON LA TARJETA : 5489133182050904 EL 2025-10-10"
  },
  {
    "text": "MARTIN BARROSO JAVIER",
    "label": "Transporte",
    "confidence": 0.6707,
    "original": "TRANSFERENCIA A FAVOR DE MARTIN BARROSO JAVIER"
  },
  {
    "text": "MARTIN BARROSO JAVIER",
    "label": "Transporte",
    "confidence": 0.6707,
    "original": "TRANSFERENCIA A FAVOR DE MARTIN BARROSO JAVIER"
  },
  {
    "text": "BIZUM DE GLORIA B J CONCEPTO Cumple",
    "label": "Otros",
    "confidence": 0.8419,
    "original": "BIZUM DE GLORIA B J CONCEPTO Cumple"
  },
  {
    "text": "MARTIN BARROSO JAVIER",
    "label": "Transporte",
    "confidence": 0.6707,
    "original": "TRANSFERENCIA A FAVOR DE MARTIN BARROSO JAVIER"
  },
  {
    "text": "MARTIN BARROSO JAVIER",
    "label": "Transporte",
    "confidence": 0.6707,
    "original": "TRANSFERENCIA A FAVOR DE MARTIN BARROSO JAVIER"
  },
  {
    "text": "Samsung pay COMPRA EN TVR EMV MADRID",
    "label": "Tecnología",
    "confidence": 0.6399,
    "original": "Samsung pay: COMPRA EN TVR EMV MADRID, CON LA TARJETA : 5489133182050904 EL 2025-06-12"
  },
  {
    "text": "MARTIN BARROSO JAVIER",
    "label": "Transporte",
    "confidence": 0.6707,
    "original": "TRANSFERENCIA A FAVOR DE MARTIN BARROSO JAVIER"
  },
  {
    "text": "BIZUM DE JUAN CARLOS CANDENAS PORTILLO CONCEPTO Desayuno",
    "label": "Otros",
    "confidence": 0.3058,
    "original": "BIZUM DE JUAN CARLOS CANDENAS PORTILLO CONCEPTO Desayuno"
  },
  {
    "text": "MARTIN BARROSO JAVIER",
    "label": "Transporte",
    "confidence": 0.6707,
    "original": "TRANSFERENCIA A FAVOR DE MARTIN BARROSO JAVIER"
  },
  {
    "text": "MARTIN BARROSO JAVIER",
    "label": "Transporte",
    "confidence": 0.6707,
    "original": "TRANSFERENCIA A FAVOR DE MARTIN BARROSO JAVIER"
  },
  {
    "text": "MARTIN BARROSO JAVIER",
    "label": "Transporte",
    "confidence": 0.6707,
    "original": "TRANSFERENCIA A FAVOR DE MARTIN BARROSO JAVIER"
  },
  {
    "text": "MARTIN BARROSO JAVIER",
    "label": "Transporte",
    "confidence": 0.6707,
    "original": "TRANSFERENCIA A FAVOR DE MARTIN BARROSO JAVIER"
  },
  {
    "text": "aliexpress",
    "label": "Otros",
    "confidence": 0.6757,
    "original": "COMPRA EN aliexpress, CON LA TARJETA : 5489133182050904 EL 2025-01-31"
  },
  {
    "text": "aliexpress",
    "label": "Otros",
    "confidence": 0.6757,
    "original": "COMPRA EN aliexpress, CON LA TARJETA : 5489133182050904 EL 2025-01-28"
  },
  {
    "text": "aliexpress",
    "label": "Otros",
    "confidence": 0.6757,
    "original": "COMPRA EN aliexpress, CON LA TARJETA : 5489133182050904 EL 2025-01-05"
  },
  {
    "text": "BIZUM DE MACRINA BARROSO JIMENEZ CONCEPTO Comida Reyes",
    "label": "Otros",
    "confidence": 0.8286,
    "original": "BIZUM DE MACRINA BARROSO JIMENEZ CONCEPTO Comida Reyes"
  },
  {
    "text": "MARTIN BARROSO JAVIER",
    "label": "Transporte",
    "confidence": 0.6707,
    "original": "TRANSFERENCIA A FAVOR DE MARTIN BARROSO JAVIER"
  },
  {
    "text": "MARTIN BARROSO JAVIER",
    "label": "Transporte",
    "confidence": 0.6707,
    "original": "TRANSFERENCIA A FAVOR DE MARTIN BARROSO JAVIER"
  },
  {
    "text": "BIZUM DE MACRINA BARROSO JIMENEZ CONCEPTO licor d cerezas",
    "label": "Hogar",
    "confidence": 0.5014,
    "original": "BIZUM DE MACRINA BARROSO JIMENEZ CONCEPTO licor d cerezas"
  },
  {
    "text": "Samsung pay COMPRA EN IKEA LEGANES FOOD",
    "label": "Tecnología",
    "confidence": 0.8038,
    "original": "Samsung pay: COMPRA EN IKEA LEGANES FOOD, CON LA TARJETA : 5489133182050904 EL 2024-12-20"
  },
  {
    "text": "MARTIN BARROSO JAVIER",
    "label": "Transporte",
    "confidence": 0.6707,
    "original": "TRANSFERENCIA A FAVOR DE MARTIN BARROSO JAVIER"
  },
  {
    "text": "Gaijin Games",
    "label": "Otros",
    "confidence": 0.4168,
    "original": "COMPRA EN Gaijin Games, CON LA TARJETA : 5489133182050904 EL 2024-12-13"
  },
  {
    "text": "MARTIN BARROSO JAVIER",
    "label": "Transporte",
    "confidence": 0.6707,
    "original": "TRANSFERENCIA A FAVOR DE MARTIN BARROSO JAVIER"
  },
  {
    "text": "Samsung pay COMPRA EN MAXIDECOR",
    "label": "Tecnología",
    "confidence": 0.8499,
    "original": "Samsung pay: COMPRA EN MAXIDECOR, CON LA TARJETA : 5489133182050904 EL 2024-11-25"
  },
  {
    "text": "NASCAPERS",
    "label": "Otros",
    "confidence": 0.8126,
    "original": "COMPRA EN NASCAPERS, CON LA TARJETA : 5489133182050904 EL 2024-11-12"
  },
  {
    "text": "MARTIN BARROSO JAVIER",
    "label": "Transporte",
    "confidence": 0.6707,
    "original": "TRANSFERENCIA A FAVOR DE MARTIN BARROSO JAVIER"
  },
  {
    "text": "Samsung pay COMPRA EN LIVI ESTILISTAS",
    "label": "Ocio",
    "confidence": 0.6519,
    "original": "Samsung pay: COMPRA EN LIVI ESTILISTAS, CON LA TARJETA : 5489133182050904 EL 2024-09-20"
  },
  {
    "text": "MARTIN BARROSO JAVIER",
    "label": "Transporte",
    "confidence": 0.6707,
    "original": "TRANSFERENCIA A FAVOR DE MARTIN BARROSO JAVIER"
  },
  {
    "text": "Aquazel SL CONCEPTO Acuario Javier Martin",
    "label": "Hogar",
    "confidence": 0.5229,
    "original": "TRANSFERENCIA A FAVOR DE Aquazel SL CONCEPTO: Acuario Javier Martin"
  },
  {
    "text": "aliexpress",
    "label": "Otros",
    "confidence": 0.6757,
    "original": "COMPRA EN aliexpress, CON LA TARJETA : 5489133182050904 EL 2024-08-31"
  },
  {
    "text": "aliexpress",
    "label": "Otros",
    "confidence": 0.6757,
    "original": "COMPRA EN aliexpress, CON LA TARJETA : 5489133182050904 EL 2024-08-19"
  },
  {
    "text": "Samsung pay COMPRA EN LIVI ESTILISTAS",
    "label": "Ocio",
    "confidence": 0.6519,
    "original": "Samsung pay: COMPRA EN LIVI ESTILISTAS, CON LA TARJETA : 5489133182050904 EL 2024-08-19"
  },
  {
    "text": "aliexpress",
    "label": "Otros",
    "confidence": 0.6757,
    "original": "COMPRA EN aliexpress, CON LA TARJETA : 5489133182050904 EL 2024-08-14"
  },
  {
    "text": "BIZUM DE MARIA JOSE BARROSO JIMENEZ CONCEPTO cumpleaños Canales Barroso",
    "label": "Otros",
    "confidence": 0.8451,
    "original": "BIZUM DE MARIA JOSE BARROSO JIMENEZ CONCEPTO cumpleaños Canales Barroso"
  },
  {
    "text": "MARTIN BARROSO JAVIER",
    "label": "Transporte",
    "confidence": 0.6707,
    "original": "TRANSFERENCIA A FAVOR DE MARTIN BARROSO JAVIER"
  },
  {
    "text": "BIZUM DE MACRINA BARROSO JIMENEZ CONCEPTO champu",
    "label": "Hogar",
    "confidence": 0.5316,
    "original": "BIZUM DE MACRINA BARROSO JIMENEZ CONCEPTO champu"
  },
  {
    "text": "AEROPUERTO LANZAROTE AIRE",
    "label": "Transporte",
    "confidence": 0.5796,
    "original": "COMPRA EN AEROPUERTO LANZAROTE AIRE, CON LA TARJETA : 5489133182050904 EL 2024-07-20"
  },
  {
    "text": "MARTIN BARROSO JAVIER",
    "label": "Transporte",
    "confidence": 0.6707,
    "original": "TRANSFERENCIA A FAVOR DE MARTIN BARROSO JAVIER"
  },
  {
    "text": "BIZUM DE MACRINA BARROSO JIMENEZ CONCEPTO Manguera pistola",
    "label": "Hogar",
    "confidence": 0.5168,
    "original": "BIZUM DE MACRINA BARROSO JIMENEZ CONCEPTO Manguera pistola."
  },
  {
    "text": "PNP Vending Orain",
    "label": "Ropa y calzado",
    "confidence": 0.4428,
    "original": "COMPRA EN PNP*Vending Orain, CON LA TARJETA : 5489133182050904 EL 2024-05-28"
  },
  {
    "text": "MARTIN BARROSO JAVIER",
    "label": "Transporte",
    "confidence": 0.6707,
    "original": "TRANSFERENCIA A FAVOR DE MARTIN BARROSO JAVIER"
  },
  {
    "text": "PNP Vending Orain",
    "label": "Ropa y calzado",
    "confidence": 0.4428,
    "original": "COMPRA EN PNP*Vending Orain, CON LA TARJETA : 5489133182050904 EL 2024-05-22"
  },
  {
    "text": "MARTIN BARROSO JAVIER",
    "label": "Transporte",
    "confidence": 0.6707,
    "original": "TRANSFERENCIA A FAVOR DE MARTIN BARROSO JAVIER"
  },
  {
    "text": "BIZUM DE MACRINA BARROSO JIMENEZ CONCEPTO televisión",
    "label": "Hogar",
    "confidence": 0.5903,
    "original": "BIZUM DE MACRINA BARROSO JIMENEZ CONCEPTO televisión"
  },
  {
    "text": "PNP Vending Orain",
    "label": "Ropa y calzado",
    "confidence": 0.4428,
    "original": "COMPRA EN PNP*Vending Orain, CON LA TARJETA : 5489133182050904 EL 2024-04-17"
  },
  {
    "text": "Samsung pay COMPRA EN CHURRERIA MADRID 1883",
    "label": "Tecnología",
    "confidence": 0.7009,
    "original": "Samsung pay: COMPRA EN CHURRERIA MADRID 1883, CON LA TARJETA : 5489133182050904 EL 2024-04-12"
  },
  {
    "text": "MARTIN BARROSO JAVIER",
    "label": "Transporte",
    "confidence": 0.6707,
    "original": "TRANSFERENCIA A FAVOR DE MARTIN BARROSO JAVIER"
  },
  {
    "text": "aliexpress",
    "label": "Otros",
    "confidence": 0.6757,
    "original": "COMPRA EN aliexpress, CON LA TARJETA : 5489133182050904 EL 2024-03-25"
  },
  {
    "text": "BIZUM DE MACRINA BARROSO JIMENEZ CONCEPTO Tronco",
    "label": "Otros",
    "confidence": 0.5987,
    "original": "BIZUM DE MACRINA BARROSO JIMENEZ CONCEPTO Tronco"
  }
]